vltconfig/__init__.py
vltconfig/config.py
vltconfig/constants.py
vltconfig/json_source.py
vltconfig/vault_source.py
vltconfig-1.0.1.dist-info/METADATA
vltconfig-1.0.1.dist-info/WHEEL
vltconfig-1.0.1.dist-info/top_level.txt
vltconfig-1.0.1.dist-info/RECORD
