Metadata-Version: 2.4
Name: vltconfig
Version: 1.0.1
Summary: Pydantic settings from HashiCorp Vault KV and JSON with caching and retry
Author-email: tofuurem <rabbit_1399@icloud.com>
License: MIT
Project-URL: Homepage, https://github.com/tofuurem/vltconfig
Project-URL: Repository, https://github.com/tofuurem/vltconfig
Project-URL: Issues, https://github.com/tofuurem/vltconfig/issues
Classifier: Programming Language :: Python
Classifier: Programming Language :: Python :: 3
Classifier: Programming Language :: Python :: 3.11
Classifier: Programming Language :: Python :: 3.12
Classifier: Programming Language :: Python :: 3.13
Requires-Python: >=3.11
Requires-Dist: hvac>=2.3.0
Requires-Dist: loguru>=0.7.3
Requires-Dist: pydantic>=2.10.6
Requires-Dist: pydantic-settings>=2.7.1
Requires-Dist: tenacity>=9.0.0
